lusid_notifications/__init__.py
lusid_notifications/__version__.py
lusid_notifications/api_client.py
lusid_notifications/configuration.py
lusid_notifications/exceptions.py
lusid_notifications/rest.py
lusid_notifications/api/__init__.py
lusid_notifications/api/application_metadata_api.py
lusid_notifications/api/deliveries_api.py
lusid_notifications/api/event_types_api.py
lusid_notifications/api/events_api.py
lusid_notifications/api/notifications_api.py
lusid_notifications/api/subscriptions_api.py
lusid_notifications/models/__init__.py
lusid_notifications/models/access_controlled_action.py
lusid_notifications/models/access_controlled_resource.py
lusid_notifications/models/action_id.py
lusid_notifications/models/attempt.py
lusid_notifications/models/attempt_status.py
lusid_notifications/models/create_aws_sqs_notification.py
lusid_notifications/models/create_aws_sqs_principal_auth_notification.py
lusid_notifications/models/create_azure_service_bus_notification.py
lusid_notifications/models/create_email_notification.py
lusid_notifications/models/create_sms_notification.py
lusid_notifications/models/create_subscription.py
lusid_notifications/models/create_webhook_notification.py
lusid_notifications/models/delivery.py
lusid_notifications/models/event_details.py
lusid_notifications/models/event_field_definition.py
lusid_notifications/models/event_type_schema.py
lusid_notifications/models/id_selector_definition.py
lusid_notifications/models/identifier_part_schema.py
lusid_notifications/models/link.py
lusid_notifications/models/lusid_problem_details.py
lusid_notifications/models/lusid_validation_problem_details.py
lusid_notifications/models/matching_pattern.py
lusid_notifications/models/notification.py
lusid_notifications/models/notification_status.py
lusid_notifications/models/resource_id.py
lusid_notifications/models/resource_list_of_access_controlled_resource.py
lusid_notifications/models/resource_list_of_delivery.py
lusid_notifications_sdk_preview-0.1.1057.dist-info/METADATA
lusid_notifications_sdk_preview-0.1.1057.dist-info/WHEEL
lusid_notifications_sdk_preview-0.1.1057.dist-info/top_level.txt
lusid_notifications_sdk_preview-0.1.1057.dist-info/RECORD
